{
  "project_info": {
    "project_number": "991071408047",
    "project_id": "macc-6dcf0",
    "storage_bucket": "macc-6dcf0.appspot.com"
  },
  "client": [
    {
      "client_info": {
        "mobilesdk_app_id": "1:991071408047:android:9704eb7452ed70eca8a95a",
        "android_client_info": {
          "package_name": "com.example.cuadro"
        }
      },
      "oauth_client": [
        {
          "client_id": "991071408047-raadpvomfn39r079721jqlrufcto4pu8.apps.googleusercontent.com",
          "client_type": 1,
          "android_info": {
            "package_name": "com.example.cuadro",
            "certificate_hash": "1641c4d0d76163817e0c37f9f2fa3ee59d4683e7"
          }
        },
        {
          "client_id": "991071408047-rhgoec5gnenl17r49vtb96k82l10aflf.apps.googleusercontent.com",
          "client_type": 3
        }
      ],
      "api_key": [
        {
          "current_key": "AIzaSyC6qa6rn-gx3Nx0UYd1irKC9SUKiSSuys0"
        }
      ],
      "services": {
        "appinvite_service": {
          "other_platform_oauth_client": [
            {
              "client_id": "991071408047-rhgoec5gnenl17r49vtb96k82l10aflf.apps.googleusercontent.com",
              "client_type": 3
            },
            {
              "client_id": "991071408047-idu3grfietjspeln30m1n0fkoju1110j.apps.googleusercontent.com",
              "client_type": 2,
              "ios_info": {
                "bundle_id": "com.example.cuadro"
              }
            }
          ]
        }
      }
    }
  ],
  "configuration_version": "1"
}